frontveg/__init__.py
frontveg/_version.py
frontveg/_widget.py
frontveg/napari.yaml
frontveg/utils.py
frontveg/_tests/__init__.py
frontveg/_tests/test_widget.py
frontveg-0.3.5.dist-info/licenses/LICENSE
frontveg-0.3.5.dist-info/METADATA
frontveg-0.3.5.dist-info/WHEEL
frontveg-0.3.5.dist-info/entry_points.txt
frontveg-0.3.5.dist-info/top_level.txt
frontveg-0.3.5.dist-info/RECORD
