Metadata-Version: 2.4
Name: frontveg
Version: 0.3.5
Summary: Segmentation of vegetation located to close to camera
Author: Herearii Metuarea
Author-email: herearii.metuarea@univ-angers.fr
License: 
Project-URL: Bug Tracker, https://github.com/hereariim/frontveg/issues
Project-URL: Documentation, https://github.com/hereariim/frontveg#README.md
Project-URL: Source Code, https://github.com/hereariim/frontveg
Project-URL: User Support, https://github.com/hereariim/frontveg/issues
Classifier: Development Status :: 2 - Pre-Alpha
Classifier: Framework :: napari
Classifier: Intended Audience :: Developers
Classifier: License :: OSI Approved :: BSD License
Classifier: Operating System :: OS Independent
Classifier: Programming Language :: Python
Classifier: Programming Language :: Python :: 3
Classifier: Programming Language :: Python :: 3 :: Only
Classifier: Programming Language :: Python :: 3.10
Classifier: Programming Language :: Python :: 3.11
Classifier: Programming Language :: Python :: 3.12
Classifier: Programming Language :: Python :: 3.13
Classifier: Topic :: Scientific/Engineering :: Image Processing
Requires-Python: ==3.11.12
License-File: LICENSE
Requires-Dist: numpy
Requires-Dist: magicgui
Requires-Dist: qtpy
Requires-Dist: scikit-image
Requires-Dist: transformers==4.51.3
Requires-Dist: torch>=2.3.1
Requires-Dist: torchvision>=0.18.1
Requires-Dist: hydra-core==1.3.2
Requires-Dist: iopath>=0.1.10
Requires-Dist: pillow>=9.4.0
Requires-Dist: sam2==1.1.0
Provides-Extra: testing
Requires-Dist: tox; extra == "testing"
Requires-Dist: pytest; extra == "testing"
Requires-Dist: pytest-cov; extra == "testing"
Requires-Dist: pytest-qt; extra == "testing"
Requires-Dist: napari; extra == "testing"
Requires-Dist: pyqt5; extra == "testing"
Dynamic: license-file
